arkparse/__init__.py
arkparse/ark_tribe.py
arkparse/api/__init__.py
arkparse/api/base_api.py
arkparse/api/dino_api.py
arkparse/api/equipment_api.py
arkparse/api/general_api.py
arkparse/api/json_api.py
arkparse/api/player_api.py
arkparse/api/rcon_api.py
arkparse/api/stackable_api.py
arkparse/api/structure_api.py
arkparse/assets/ABERRATION.PNG
arkparse/assets/RAGNAROK.PNG
arkparse/assets/THE_ISLAND.PNG
arkparse/assets/__init__.py
arkparse/assets/heavy_inventory
arkparse/assets/tamable_dinos.txt
arkparse/assets/templates/equipment/armor
arkparse/assets/templates/equipment/armor_bp
arkparse/assets/templates/equipment/armor_bp_n.json
arkparse/assets/templates/equipment/armor_n.json
arkparse/assets/templates/equipment/saddle
arkparse/assets/templates/equipment/saddle_bp
arkparse/assets/templates/equipment/saddle_bp_n.json
arkparse/assets/templates/equipment/saddle_n.json
arkparse/assets/templates/equipment/shield
arkparse/assets/templates/equipment/shield_bp
arkparse/assets/templates/equipment/shield_bp_n.json
arkparse/assets/templates/equipment/shield_n.json
arkparse/assets/templates/equipment/weapon
arkparse/assets/templates/equipment/weapon_bp
arkparse/assets/templates/equipment/weapon_bp_n.json
arkparse/assets/templates/equipment/weapon_n.json
arkparse/assets/templates/inventory/with_item_n.json
arkparse/assets/templates/stackable/stackable
arkparse/assets/templates/stackable/stackable_n.json
arkparse/classes/__init__.py
arkparse/classes/consumables.py
arkparse/classes/dinos.py
arkparse/classes/equipment.py
arkparse/classes/placed_structures.py
arkparse/classes/player.py
arkparse/classes/resources.py
arkparse/enums/__init__.py
arkparse/enums/ark_dino_trait.py
arkparse/enums/ark_enum.py
arkparse/enums/ark_equipment_stat.py
arkparse/enums/ark_item_quality.py
arkparse/enums/ark_map.py
arkparse/enums/ark_stat.py
arkparse/ftp/__init__.py
arkparse/ftp/ark_ftp_client.py
arkparse/helpers/dino/is_wild_tamed.py
arkparse/logging/__init__.py
arkparse/logging/ark_save_logger.py
arkparse-0.3.9.dist-info/METADATA
arkparse-0.3.9.dist-info/WHEEL
arkparse-0.3.9.dist-info/licenses/LICENSE
arkparse-0.3.9.dist-info/RECORD
