Metadata-Version: 2.4
Name: arkparse
Version: 0.3.9
Summary: A package to parse and modify ark save files
Project-URL: Homepage, https://github.com/VincentHenauGithub/ark-save-parser
Author-email: Vincent Henau <vincent.henau.github@gmail.com>
License-File: LICENSE
Classifier: Programming Language :: Python :: 3
Requires-Python: >=3.9
Requires-Dist: matplotlib>=3.10.3
Requires-Dist: numpy>=2.3.2
Requires-Dist: pandas>=2.3.1
Requires-Dist: rcon>=2.4.9
